nonebot_plugin_funticon-0.1.0.dist-info/METADATA
nonebot_plugin_funticon-0.1.0.dist-info/WHEEL
nonebot_plugin_funticon-0.1.0.dist-info/entry_points.txt
nonebot_plugin_funticon/__init__.py
nonebot_plugin_funticon/config.py
nonebot_plugin_funticon-0.1.0.dist-info/RECORD
