Metadata-Version: 2.1
Name: nonebot_plugin_funticon
Version: 0.1.0
Summary: Nonebot2 插件：群工具
Author-Email: EnderKylin <3162176860@qq.com>
License: MIT
Requires-Python: >=3.9
Requires-Dist: aiohttp>=3.12.15
Requires-Dist: nonebot-adapter-onebot>=2.4.6
Requires-Dist: nonebot2>=2.3.1
